{
  "project_info": {
    "project_number": "246835149092",
    "project_id": "rabunabi-95b35",
    "storage_bucket": "rabunabi-95b35.appspot.com"
  },
  "client": [
    {
      "client_info": {
        "mobilesdk_app_id": "1:246835149092:android:fe8512d7f8cb9cb22d9bb1",
        "android_client_info": {
          "package_name": "com.rabunabi.friends"
        }
      },
      "oauth_client": [
        {
          "client_id": "246835149092-ou8sqoe3c0rss33jhnok1jnrn78i3inv.apps.googleusercontent.com",
          "client_type": 3
        }
      ],
      "api_key": [
        {
          "current_key": "AIzaSyDIZzg_LID_WVkYiRs4AxSvXNZdZejUhQw"
        }
      ],
      "services": {
        "appinvite_service": {
          "other_platform_oauth_client": [
            {
              "client_id": "246835149092-ou8sqoe3c0rss33jhnok1jnrn78i3inv.apps.googleusercontent.com",
              "client_type": 3
            }
          ]
        }
      }
    }
  ],
  "configuration_version": "1"
}